pyzabbix/__init__.py
pyzabbix/api.py
pyzabbix/py.typed
pyzabbix-1.3.1.dist-info/METADATA
pyzabbix-1.3.1.dist-info/WHEEL
pyzabbix-1.3.1.dist-info/top_level.txt
pyzabbix-1.3.1.dist-info/RECORD
